gub/__init__.py
gub/ghubscan.py
gub-1.4.0.dist-info/METADATA
gub-1.4.0.dist-info/WHEEL
gub-1.4.0.dist-info/entry_points.txt
gub-1.4.0.dist-info/top_level.txt
gub-1.4.0.dist-info/RECORD
