Metadata-Version: 2.2
Name: gub
Version: 1.4.0
Summary: GhubScan OSINT Tool for GitHub
Home-page: https://github.com/banaxou/GhubScan
Author: ovax
Classifier: Programming Language :: Python :: 3
Classifier: License :: OSI Approved :: MIT License
Classifier: Operating System :: OS Independent
Requires-Python: >=3.6
Requires-Dist: requests
Requires-Dist: fade
Requires-Dist: argparse
Dynamic: author
Dynamic: classifier
Dynamic: description
Dynamic: description-content-type
Dynamic: home-page
Dynamic: requires-dist
Dynamic: requires-python
Dynamic: summary
